connexity/__init__.py
connexity/client.py
connexity/constants.py
connexity/calls/__init__.py
connexity/calls/call_session.py
connexity/calls/models.py
connexity/calls/messages/__init__.py
connexity/calls/messages/assistant_message.py
connexity/calls/messages/base_message.py
connexity/calls/messages/interface_message.py
connexity/calls/messages/issue_message.py
connexity/calls/messages/tool_call_message.py
connexity/calls/messages/tool_result_message.py
connexity/calls/messages/user_message.py
connexity/pipecat/__init__.py
connexity/pipecat/base_observer.py
connexity/pipecat/daily.py
connexity/pipecat/tool_observer.py
connexity/pipecat/twilio.py
connexity/pipecat/utils/__init__.py
connexity/pipecat/utils/detect_interruption_loops.py
connexity/pipecat/utils/get_daily_recording_url.py
connexity/pipecat/utils/observer_utils.py
connexity/pipecat/utils/twilio_module.py
connexity/utils/__init__.py
connexity/utils/connexity_api.py
connexity/utils/logging_config.py
connexity/utils/snapshot_error_frame.py
connexity/utils/trace_observer.py
connexity-1.0.1.dist-info/METADATA
connexity-1.0.1.dist-info/WHEEL
connexity-1.0.1.dist-info/top_level.txt
connexity-1.0.1.dist-info/RECORD
