Metadata-Version: 2.4
Name: connexity
Version: 1.0.1
Summary: A Python client for Connexity API.
Author-email: Dima Ulyanets <dima@spacestep.ca>, Maksym Ilin <maksym@spacestep.ca>, Mykhailo Humeniuk <mykhailo.humeniuk@spacestep.ca>
License: MIT
Requires-Python: >=3.11
Requires-Dist: aiohttp
Requires-Dist: python-dotenv
Requires-Dist: pipecat-ai>=0.0.67
Provides-Extra: dev
Requires-Dist: autoflake>=2.3.1; extra == "dev"
Requires-Dist: ruff>=0.14.9; extra == "dev"
